aify/__init__.py
aify/__main__.py
aify/_auth.py
aify/_entry.py
aify/_env.py
aify/_error.py
aify/_logging.py
aify/_program.py
aify/_web_template.py
aify/embeddings.py
aify/embeddings_openai.py
aify/embeddings_sentence_transformers.py
aify/memory.py
aify/memories/__init__.py
aify/memories/google_cloud_datastore.py
aify-0.1.23.data/scripts/aify
aify-0.1.23.data/scripts/requirements.txt
aify-0.1.23.data/scripts/setup.py
webui/__init__.py
webui/static/aify/aify.css
webui/static/aify/aify.css.map
webui/static/aify/aify.js
webui/static/aify/aify.js.LICENSE.txt
webui/static/aify/aify.js.map
webui/templates/auth.html
webui/templates/basic.html
webui/templates/index.html
aify-0.1.23.dist-info/LICENSE
aify-0.1.23.dist-info/METADATA
aify-0.1.23.dist-info/WHEEL
aify-0.1.23.dist-info/top_level.txt
aify-0.1.23.dist-info/RECORD
