Metadata-Version: 2.1
Name: aify
Version: 0.1.23
Summary: aify is an AI-native application framework and runtime
Home-page: https://github.com/shellc/aify
Author-email: shenggong.wang@gmail.com
Keywords: AI-Native,LLM,aify,chatbot
License-File: LICENSE
Requires-Dist: guidance
Requires-Dist: pyyaml
Requires-Dist: openai
Requires-Dist: pandas
Requires-Dist: numpy
Requires-Dist: uvicorn
Requires-Dist: starlette
Requires-Dist: fastapi
Requires-Dist: jinja2
Requires-Dist: python-multipart
Requires-Dist: python-dotenv
Requires-Dist: watchfiles
